Atlas.cpython-310-darwin.so
atlas_finance_noad-2.1.0.dist-info/METADATA
atlas_finance_noad-2.1.0.dist-info/WHEEL
atlas_finance_noad-2.1.0.dist-info/top_level.txt
atlas_finance_noad-2.1.0.dist-info/RECORD
