Metadata-Version: 2.1
Name: atlas-finance-noad
Version: 2.1.0
Summary: Pricing library for Python
Author: Jose Melo
Author-email: jmelo@live.cl
Requires-Python: >=3.7
